{"NAME": "NNN", "Summary": "None", "Loss": 0.6443957686424255, "Accuracy": 0.6455696225166321, "Classification Report": "              precision    recall  f1-score   support\n\n       anger     0.7395    0.6667    0.7012       345\n         sad     0.5248    0.6106    0.5644       208\n\n   micro avg     0.6456    0.6456    0.6456       553\n   macro avg     0.6322    0.6386    0.6328       553\nweighted avg     0.6588    0.6456    0.6498       553\n samples avg     0.6456    0.6456    0.6456       553\n", "Confusion_matrix": [[0.6666666666666666, 0.3333333333333333], [0.3894230769230769, 0.6105769230769231]]}