{"NAME": "NNN", "Summary": "None", "Loss": 0.6613596081733704, "Accuracy": 0.6295620203018188, "Classification Report": "              precision    recall  f1-score   support\n\n       anger     0.7686    0.5765    0.6588       340\n         sad     0.5085    0.7163    0.5948       208\n\n   micro avg     0.6296    0.6296    0.6296       548\n   macro avg     0.6386    0.6464    0.6268       548\nweighted avg     0.6699    0.6296    0.6345       548\n samples avg     0.6296    0.6296    0.6296       548\n", "Confusion_matrix": [[0.5764705882352941, 0.4235294117647059], [0.28365384615384615, 0.7163461538461539]]}