{"NAME": "NNN", "Summary": "None", "Loss": 1.1682751178741455, "Accuracy": 0.7215189933776855, "Classification Report": "              precision    recall  f1-score   support\n\n       anger     0.7868    0.7594    0.7729       345\n     sadness     0.6227    0.6587    0.6402       208\n\n   micro avg     0.7215    0.7215    0.7215       553\n   macro avg     0.7048    0.7090    0.7065       553\nweighted avg     0.7251    0.7215    0.7230       553\n samples avg     0.7215    0.7215    0.7215       553\n", "Confusion_matrix": [[0.7594202898550725, 0.24057971014492754], [0.34134615384615385, 0.6586538461538461]]}